README.rst
setup.py
aws_utils/__init__.py
aws_utils/exceptions.py
aws_utils/s3_connector.py
aws_utils/sns_pubsub_connector.py
aws_utils/sqs_consumer.py
aws_utils.egg-info/PKG-INFO
aws_utils.egg-info/SOURCES.txt
aws_utils.egg-info/dependency_links.txt
aws_utils.egg-info/requires.txt
aws_utils.egg-info/top_level.txt