Metadata-Version: 1.0
Name: aws-utils
Version: 0.1
Summary: aws utilities package
Home-page: https://github.com/thuitaw/aws-utils.git
Author: Thuita Wachira
Author-email: UNKNOWN
License: GPL
Keywords: utilities utils aws
Platform: UNKNOWN
